noashark/__init__.py
noashark/dem.py
noashark/download.py
noashark/fema.py
noashark-0.1.1.dist-info/LICENSE
noashark-0.1.1.dist-info/METADATA
noashark-0.1.1.dist-info/WHEEL
noashark-0.1.1.dist-info/top_level.txt
noashark-0.1.1.dist-info/RECORD
